xspider/__init__.py
xspider/__main__.py
xspider/client.py
xspider/config.py
xspider/extensions.py
xspider/items.py
xspider/loaders.py
xspider/middlewares.py
xspider/pipelines.py
xspider/server.py
xspider/settings.py
xspider/core/Preprocessor.py
xspider/core/Xspider.py
xspider/core/__init__.py
xspider/spiders/XspiderSpider.py
xspider/spiders/__init__.py
xspider/utils/__init__.py
xspider/utils/connection.py
xspider/utils/defaults.py
xspider/utils/exceptions.py
xspider/utils/log.py
xspider/utils/parser.py
xspider/utils/task.py
xspider/utils/xmlparse.py
pyxspider-1.2.dist-info/METADATA
pyxspider-1.2.dist-info/WHEEL
pyxspider-1.2.dist-info/entry_points.txt
pyxspider-1.2.dist-info/top_level.txt
pyxspider-1.2.dist-info/RECORD
